mysqlkit/__init__.py
mysqlkit/rpl/__init__.py
mysqlkit/rpl/gtid.py
mysqlkit-1.0.3.dist-info/LICENSE
mysqlkit-1.0.3.dist-info/METADATA
mysqlkit-1.0.3.dist-info/WHEEL
mysqlkit-1.0.3.dist-info/top_level.txt
mysqlkit-1.0.3.dist-info/RECORD
