Metadata-Version: 2.1
Name: mysqlkit
Version: 1.0.3
Summary: Python libraries for managing MySQL
Home-page: UNKNOWN
Author: Karoly Nagy
Author-email: dr.karoly.nagy@gmail.com
License: MIT
Platform: UNKNOWN
Classifier: Development Status :: 4 - Beta
Classifier: Programming Language :: Python :: 2
Classifier: Programming Language :: Python :: 2.7
Classifier: Programming Language :: Python :: 3
Classifier: Programming Language :: Python :: 3.5
Classifier: Programming Language :: Python :: 3.6
